core/__init__.py
core/checker.py
core/config_manager.py
core/data_collector.py
core/database.py
core/parser.py
core/repository_analyzer.py
core/scheduler.py
deprecated_checker-1.0.31.dist-info/licenses/LICENSE
utils/__init__.py
utils/cli.py
deprecated_checker-1.0.31.dist-info/METADATA
deprecated_checker-1.0.31.dist-info/WHEEL
deprecated_checker-1.0.31.dist-info/entry_points.txt
deprecated_checker-1.0.31.dist-info/top_level.txt
deprecated_checker-1.0.31.dist-info/RECORD
