Metadata-Version: 2.4
Name: deprecated-checker
Version: 1.0.31
Summary: Tool for checking deprecated dependencies in Python projects and suggesting alternatives
Home-page: https://github.com/julicq/deprecated-checker
Author: Iulian Pavlov
Author-email: Iulian Pavlov <iulianpavlov@icloud.com>
Maintainer-email: Iulian Pavlov <iulianpavlov@icloud.com>
License-Expression: MIT
Project-URL: Homepage, https://github.com/julicq/is-deprecated-or-not
Project-URL: Documentation, https://github.com/julicq/is-deprecated-or-not#readme
Project-URL: Repository, https://github.com/julicq/is-deprecated-or-not
Project-URL: Issues, https://github.com/julicq/is-deprecated-or-not/issues
Project-URL: Changelog, https://github.com/julicq/is-deprecated-or-not/releases
Keywords: dependencies,deprecated,security,python,cli
Classifier: Development Status :: 4 - Beta
Classifier: Intended Audience :: Developers
Classifier: Operating System :: OS Independent
Classifier: Programming Language :: Python :: 3
Classifier: Programming Language :: Python :: 3.8
Classifier: Programming Language :: Python :: 3.9
Classifier: Programming Language :: Python :: 3.10
Classifier: Programming Language :: Python :: 3.11
Classifier: Topic :: Software Development :: Libraries :: Python Modules
Classifier: Topic :: Software Development :: Quality Assurance
Classifier: Topic :: System :: Systems Administration
Requires-Python: >=3.8
License-File: LICENSE
Requires-Dist: typer>=0.9.0
Requires-Dist: rich>=13.0.0
Requires-Dist: pyyaml>=6.0
Requires-Dist: requests>=2.28.0
Requires-Dist: packaging>=23.0
Requires-Dist: toml>=0.10.0
Requires-Dist: schedule>=1.2.0
Provides-Extra: dev
Requires-Dist: pytest>=7.0.0; extra == "dev"
Requires-Dist: pytest-cov>=4.0.0; extra == "dev"
Requires-Dist: black>=23.0.0; extra == "dev"
Requires-Dist: flake8>=6.0.0; extra == "dev"
Requires-Dist: mypy>=1.0.0; extra == "dev"
Dynamic: author
Dynamic: home-page
Dynamic: license-file
Dynamic: requires-python
